django_admin_multi_select_filter/__init__.py
django_admin_multi_select_filter/filters.py
django_admin_multi_select_filter-1.4.1.dist-info/LICENSE
django_admin_multi_select_filter-1.4.1.dist-info/METADATA
django_admin_multi_select_filter-1.4.1.dist-info/WHEEL
django_admin_multi_select_filter-1.4.1.dist-info/top_level.txt
django_admin_multi_select_filter-1.4.1.dist-info/RECORD
