Metadata-Version: 2.1
Name: django-admin-multi-select-filter
Version: 1.4.1
Summary: Django admin filter for multiple select
Author-email: Job Doesburg <job.doesburg@gmail.com>
License: MIT License
Project-URL: homepage, https://github.com/JobDoesburg/django-admin-multi-select-filter
Project-URL: repository, https://github.com/JobDoesburg/django-admin-multi-select-filter
Project-URL: documentation, https://github.com/JobDoesburg/django-admin-multi-select-filter
Classifier: License :: OSI Approved :: MIT License
Classifier: Programming Language :: Python
Classifier: Programming Language :: Python :: 3
Classifier: Framework :: Django
Classifier: Framework :: Django :: 3.0
Classifier: Framework :: Django :: 3.1
Classifier: Framework :: Django :: 3.2
Classifier: Framework :: Django :: 4.0
Classifier: Framework :: Django :: 4.1
Classifier: Framework :: Django :: 4.2
Classifier: Framework :: Django :: 5.0
Classifier: Intended Audience :: Developers
Classifier: Operating System :: OS Independent
Requires-Python: >=3
License-File: LICENSE
Requires-Dist: django >=3
